pierskarsenbarg_pulumi_kubeconfig/__init__.py
pierskarsenbarg_pulumi_kubeconfig/_utilities.py
pierskarsenbarg_pulumi_kubeconfig/aks_kube_config.py
pierskarsenbarg_pulumi_kubeconfig/eks_kube_config.py
pierskarsenbarg_pulumi_kubeconfig/gke_kube_config.py
pierskarsenbarg_pulumi_kubeconfig/provider.py
pierskarsenbarg_pulumi_kubeconfig/pulumi-plugin.json
pierskarsenbarg_pulumi_kubeconfig/py.typed
pierskarsenbarg_pulumi_kubeconfig-0.3.0.dist-info/METADATA
pierskarsenbarg_pulumi_kubeconfig-0.3.0.dist-info/WHEEL
pierskarsenbarg_pulumi_kubeconfig-0.3.0.dist-info/top_level.txt
pierskarsenbarg_pulumi_kubeconfig-0.3.0.dist-info/RECORD
