Metadata-Version: 2.4
Name: pierskarsenbarg_pulumi_kubeconfig
Version: 0.3.0
Summary: Kubeconfig provider
License: Apache-2.0
Project-URL: Homepage, https://github.com/pierskarenbarg/pulumi-kubeconfig
Project-URL: Repository, https://github.com/pierskarenbarg/pulumi-kubeconfig
Keywords: pulumi,kubeconfig,category/infrastructure,kind/native
Requires-Python: >=3.9
Requires-Dist: parver>=0.2.1
Requires-Dist: pulumi<4.0.0,>=3.0.0
Requires-Dist: pulumi_azure_native<3.0.0,>=2.0.0
Requires-Dist: semver>=2.8.1
Requires-Dist: typing-extensions<5,>=4.11; python_version < "3.11"
